llama_index/postprocessor/longllmlingua/__init__.py
llama_index/postprocessor/longllmlingua/base.py
llama_index_postprocessor_longllmlingua-0.5.1.dist-info/METADATA
llama_index_postprocessor_longllmlingua-0.5.1.dist-info/WHEEL
llama_index_postprocessor_longllmlingua-0.5.1.dist-info/licenses/LICENSE
llama_index_postprocessor_longllmlingua-0.5.1.dist-info/RECORD
